etc/Executors.py
etc/__init__.py
etc/base.py
etc/cli.py
etc/default_descriptors.py
etc/main_class.py
etc/main_e2e.py
etc/main_eval.py
etc/main_repr.py
etc/setup.py
etc_ml-0.1.1.dist-info/LICENSE
etc_ml-0.1.1.dist-info/METADATA
etc_ml-0.1.1.dist-info/WHEEL
etc_ml-0.1.1.dist-info/top_level.txt
etc_ml-0.1.1.dist-info/RECORD
